LICENSE
MANIFEST.in
README.md
setup.cfg
setup.py
maitai/__init__.py
maitai/gitsha.py
maitai/prunecookies.py
maitai/renamecookie.py
maitai/securecookies.py
maitai/statuscode.py
maitai.egg-info/PKG-INFO
maitai.egg-info/SOURCES.txt
maitai.egg-info/dependency_links.txt
maitai.egg-info/not-zip-safe
maitai.egg-info/requires.txt
maitai.egg-info/top_level.txt