Metadata-Version: 1.0
Name: maitai
Version: 0.2
Summary: Handy WSGI Middleware Utilities
Home-page: http://github.com/storborg/maitai
Author: Scott Torborg
Author-email: scott@cartlogic.com
License: MIT
Keywords: wsgi middleware cookies errors
Platform: UNKNOWN
Classifier: Development Status :: 5 - Production/Stable
Classifier: License :: OSI Approved :: MIT License
Classifier: Programming Language :: Python :: 2.7
Classifier: Topic :: Internet :: WWW/HTTP :: WSGI :: Middleware
Classifier: Topic :: Internet :: WWW/HTTP :: HTTP Servers
